pdf_utility/__init__.py
pdf_utility/__main__.py
pdf_utility/image_to_pdf.py
pdf_utility/input.py
pdf_utility/pdf_utility.py
pdf_utility/util.py
scripts/format.py
scripts/generate_installer.py
scripts/test_python_source.py
tests/test_image_to_pdf.py
tests/test_inputs.py
pdf_utility-0.0.4.dist-info/LICENSE.md
pdf_utility-0.0.4.dist-info/METADATA
pdf_utility-0.0.4.dist-info/WHEEL
pdf_utility-0.0.4.dist-info/entry_points.txt
pdf_utility-0.0.4.dist-info/top_level.txt
pdf_utility-0.0.4.dist-info/RECORD
