Metadata-Version: 2.1
Name: pdf_utility
Version: 0.0.4
Summary: PDF Manipulation Utilities
Author: Sahil Kale
License: Prosperity 3.0.0
Project-URL: Homepage, https://github.com/sahil-kale/pdf-utility
Project-URL: Issues, https://github.com/sahil-kale/pdf-utility/issues
Requires-Python: >=3.7
License-File: LICENSE.md
Requires-Dist: pikepdf
Requires-Dist: pillow
Requires-Dist: click
